mcquic/__init__.py
mcquic/__main__.py
mcquic/baseClass.py
mcquic/cli.py
mcquic/config.py
mcquic/consts.py
mcquic/demo.py
mcquic/rans.cpython-39-darwin.so
mcquic/datasets/__init__.py
mcquic/datasets/__main__.py
mcquic/datasets/cli.py
mcquic/datasets/dataset.py
mcquic/datasets/transforms.py
mcquic/loss/__init__.py
mcquic/modules/__init__.py
mcquic/modules/builder.py
mcquic/modules/compound.py
mcquic/modules/compressor.py
mcquic/modules/entropyCoder.py
mcquic/modules/quantizer.py
mcquic/nn/__init__.py
mcquic/nn/base.py
mcquic/nn/blocks.py
mcquic/nn/convs.py
mcquic/nn/gdn.py
mcquic/service/__init__.py
mcquic/service/__main__.py
mcquic/service/cli.py
mcquic/service/stCompressService.py
mcquic/train/__init__.py
mcquic/train/__main__.py
mcquic/train/cli.py
mcquic/train/ddp.py
mcquic/train/hooks.py
mcquic/train/lrSchedulers.py
mcquic/train/trainer.py
mcquic/train/utils.py
mcquic/train/valueTuners.py
mcquic/utils/__init__.py
mcquic/utils/registry.py
mcquic/utils/specification.py
mcquic/utils/vision.py
mcquic/validate/__init__.py
mcquic/validate/__main__.py
mcquic/validate/cli.py
mcquic/validate/handlers.py
mcquic/validate/metrics.py
mcquic/validate/utils.py
mcquic/validate/validator.py
mcquic-0.1.40.dist-info/LICENSE
mcquic-0.1.40.dist-info/METADATA
mcquic-0.1.40.dist-info/WHEEL
mcquic-0.1.40.dist-info/entry_points.txt
mcquic-0.1.40.dist-info/top_level.txt
mcquic-0.1.40.dist-info/RECORD
