Metadata-Version: 2.1
Name: mcquic
Version: 0.1.40
Summary: McQuic, a.k.a. Multi-codebook Quantizers for neural image compression
Home-page: https://github.com/xiaosu-zhu/McQuic
Author: Xiaosu Zhu
Author-email: xiaosu.zhu@outlook.com
License: Apache-2.0 License
Keywords: image-compression,pytorch,computer-vision
Classifier: Development Status :: 3 - Alpha
Classifier: Environment :: GPU :: NVIDIA CUDA :: 11.0
Classifier: Environment :: GPU :: NVIDIA CUDA :: 11.1
Classifier: Environment :: GPU :: NVIDIA CUDA :: 11.2
Classifier: Environment :: GPU :: NVIDIA CUDA :: 11.3
Classifier: Intended Audience :: Developers
Classifier: Intended Audience :: Science/Research
Classifier: Topic :: Scientific/Engineering :: Image Processing
Classifier: License :: OSI Approved :: Apache Software License
Classifier: Programming Language :: Python :: 3.9
Requires-Python: >=3.8
License-File: LICENSE
Requires-Dist: torch (<2,>=1.10)
Requires-Dist: torchvision (<1,>=0.11)
Requires-Dist: tensorboard (<3,>=2.3)
Requires-Dist: rich (<11)
Requires-Dist: lmdb (<2)
Requires-Dist: pyyaml (<7)
Requires-Dist: marshmallow (<4)
Requires-Dist: click (<9)
Requires-Dist: vlutils (>=0.1.22)
Requires-Dist: msgpack-python (<2)
Requires-Dist: packaging
